explingo/__init__.py
explingo/grader.py
explingo/narrator.py
explingo/testing.py
explingo/tutorial.ipynb
explingo-0.1.1.dist-info/METADATA
explingo-0.1.1.dist-info/WHEEL
explingo-0.1.1.dist-info/RECORD
