Metadata-Version: 2.1
Name: explingo
Version: 0.1.1
Summary: 
Author: Ola Zytek
Author-email: zyteka@mit.edu
Requires-Python: >=3.10,<4.0
Classifier: Programming Language :: Python :: 3
Classifier: Programming Language :: Python :: 3.10
Classifier: Programming Language :: Python :: 3.11
Requires-Dist: dspy-ai (==2.4.13)
Requires-Dist: flake8 (>=7.1.1,<8.0.0)
Requires-Dist: invoke (>=2.2.0,<3.0.0)
Requires-Dist: isort (>=5.13.2,<6.0.0)
Requires-Dist: jupyter (>=1.1.1,<2.0.0)
Requires-Dist: notebook (>=7.2.2,<8.0.0)
Requires-Dist: pytest (>=8.3.3,<9.0.0)
